LICENSE
README.md
setup.py
finac/__init__.py
finac/api.py
finac/core.py
finac/currencies.py
finac/db_set.py
finac/df.py
finac/plot.py
finac.egg-info/PKG-INFO
finac.egg-info/SOURCES.txt
finac.egg-info/dependency_links.txt
finac.egg-info/requires.txt
finac.egg-info/top_level.txt